{"categories":[{"id":"d0678d38-89fc-4d2f-97d6-83a8c153624d","name":"Health","createAt":1631276403925,"updateAt":1631276403925},{"id":"edb45c9b-7335-4c00-b6cc-09c482766af6","name":"Sports","createAt":1631276403925,"updateAt":1631276403925},{"id":"d9c9b246-8f7d-457d-a5c8-026623470596","name":"Shoes","createAt":1631276403926,"updateAt":1631276403926},{"id":"bd82d69a-d2f5-4dff-86fd-23ad8dca6b12","name":"Automotive","createAt":1631276403926,"updateAt":1631276403926}],"products":[{"categoryId":"d0678d38-89fc-4d2f-97d6-83a8c153624d","id":"4d585d42-2c67-4663-8ab6-b5fcc91b34c3","name":"Unbranded Wooden Keyboard","color":"salmon","price":86,"description":"Ergonomic executive chair upholstered in bonded black leather and PVC padded seat and back for all-day comfort and support","thumbnailUrl":"http://placeimg.com/400/400","createAt":1631276403927,"updateAt":1631276403927},{"categoryId":"d0678d38-89fc-4d2f-97d6-83a8c153624d","id":"8785c2d0-a6d4-4c97-b3b0-07933264331a","name":"Practical Granite Computer","color":"mint green","price":621,"description":"The Nagasaki Lander is the trademarked name of several series of Nagasaki sport bikes, that started with the 1984 ABC800J","thumbnailUrl":"http://placeimg.com/400/400","createAt":1631276403928,"updateAt":1631276403928},{"categoryId":"d0678d38-89fc-4d2f-97d6-83a8c153624d","id":"ba3217de-07b1-4476-97ee-deb34ea73f8d","name":"Ergonomic Plastic Table","color":"turquoise","price":298,"description":"The Apollotech B340 is an affordable wireless mouse with reliable connectivity, 12 months battery life and modern design","thumbnailUrl":"http://placeimg.com/400/400","createAt":1631276403928,"updateAt":1631276403928},{"categoryId":"d0678d38-89fc-4d2f-97d6-83a8c153624d","id":"2b8e6f6f-85eb-4943-9e5b-be7280fae5ff","name":"Rustic Fresh Pants","color":"azure","price":938,"description":"Andy shoes are designed to keeping in mind durability as well as trends, the most stylish range of shoes & sandals","thumbnailUrl":"http://placeimg.com/400/400","createAt":1631276403928,"updateAt":1631276403928},{"categoryId":"d0678d38-89fc-4d2f-97d6-83a8c153624d","id":"0c05cd5a-020b-4a9c-90f8-97256cd4683e","name":"Practical Cotton Shoes","color":"teal","price":31,"description":"Ergonomic executive chair upholstered in bonded black leather and PVC padded seat and back for all-day comfort and support","thumbnailUrl":"http://placeimg.com/400/400","createAt":1631276403929,"updateAt":1631276403929},{"categoryId":"edb45c9b-7335-4c00-b6cc-09c482766af6","id":"58be3e42-7e28-41f4-b178-6ea287db905e","name":"Ergonomic Steel Car","color":"tan","price":686,"description":"The Apollotech B340 is an affordable wireless mouse with reliable connectivity, 12 months battery life and modern design","thumbnailUrl":"http://placeimg.com/400/400","createAt":1631276403929,"updateAt":1631276403929},{"categoryId":"edb45c9b-7335-4c00-b6cc-09c482766af6","id":"fdd6e6ec-8430-4e86-a236-bdba7d03aac2","name":"Handmade Wooden Chips","color":"orange","price":835,"description":"The Apollotech B340 is an affordable wireless mouse with reliable connectivity, 12 months battery life and modern design","thumbnailUrl":"http://placeimg.com/400/400","createAt":1631276403929,"updateAt":1631276403929},{"categoryId":"edb45c9b-7335-4c00-b6cc-09c482766af6","id":"acd48436-545b-46cd-841c-6ea1e19f20d7","name":"Gorgeous Frozen Bike","color":"white","price":966,"description":"New range of formal shirts are designed keeping you in mind. With fits and styling that will make you stand apart","thumbnailUrl":"http://placeimg.com/400/400","createAt":1631276403929,"updateAt":1631276403929},{"categoryId":"edb45c9b-7335-4c00-b6cc-09c482766af6","id":"5ecd6d3b-7695-4a1f-8ccc-809d0295b9c1","name":"Fantastic Metal Chair","color":"turquoise","price":241,"description":"Ergonomic executive chair upholstered in bonded black leather and PVC padded seat and back for all-day comfort and support","thumbnailUrl":"http://placeimg.com/400/400","createAt":1631276403930,"updateAt":1631276403930},{"categoryId":"edb45c9b-7335-4c00-b6cc-09c482766af6","id":"c1c94d43-2861-4ce9-a32b-bb43563aa3e0","name":"Sleek Metal Salad","color":"pink","price":782,"description":"The Nagasaki Lander is the trademarked name of several series of Nagasaki sport bikes, that started with the 1984 ABC800J","thumbnailUrl":"http://placeimg.com/400/400","createAt":1631276403930,"updateAt":1631276403930},{"categoryId":"d9c9b246-8f7d-457d-a5c8-026623470596","id":"c9d4520c-b5f6-43b6-b6c5-885ec0578ebc","name":"Handmade Fresh Chips","color":"sky blue","price":476,"description":"Boston's most advanced compression wear technology increases muscle oxygenation, stabilizes active muscles","thumbnailUrl":"http://placeimg.com/400/400","createAt":1631276403930,"updateAt":1631276403930},{"categoryId":"d9c9b246-8f7d-457d-a5c8-026623470596","id":"e5fd565c-5416-46da-a3bf-2d1626fddab3","name":"Practical Granite Chair","color":"lavender","price":825,"description":"Ergonomic executive chair upholstered in bonded black leather and PVC padded seat and back for all-day comfort and support","thumbnailUrl":"http://placeimg.com/400/400","createAt":1631276403930,"updateAt":1631276403930},{"categoryId":"d9c9b246-8f7d-457d-a5c8-026623470596","id":"2aba711f-ac19-4798-9f64-9ee666b545e2","name":"Handmade Frozen Hat","color":"orange","price":387,"description":"The automobile layout consists of a front-engine design, with transaxle-type transmissions mounted at the rear of the engine and four wheel drive","thumbnailUrl":"http://placeimg.com/400/400","createAt":1631276403931,"updateAt":1631276403931},{"categoryId":"d9c9b246-8f7d-457d-a5c8-026623470596","id":"f64e75ab-5405-4ebc-b4a5-4458c2b406ac","name":"Sleek Fresh Cheese","color":"teal","price":663,"description":"Andy shoes are designed to keeping in mind durability as well as trends, the most stylish range of shoes & sandals","thumbnailUrl":"http://placeimg.com/400/400","createAt":1631276403931,"updateAt":1631276403931},{"categoryId":"d9c9b246-8f7d-457d-a5c8-026623470596","id":"b552a423-9470-4ee7-b201-7a81ef746da4","name":"Practical Steel Shirt","color":"fuchsia","price":768,"description":"The slim & simple Maple Gaming Keyboard from Dev Byte comes with a sleek body and 7- Color RGB LED Back-lighting for smart functionality","thumbnailUrl":"http://placeimg.com/400/400","createAt":1631276403931,"updateAt":1631276403931},{"categoryId":"bd82d69a-d2f5-4dff-86fd-23ad8dca6b12","id":"22e1ae64-d925-4a3e-93e2-f26b7bba9b59","name":"Tasty Metal Keyboard","color":"violet","price":869,"description":"Andy shoes are designed to keeping in mind durability as well as trends, the most stylish range of shoes & sandals","thumbnailUrl":"http://placeimg.com/400/400","createAt":1631276403931,"updateAt":1631276403931},{"categoryId":"bd82d69a-d2f5-4dff-86fd-23ad8dca6b12","id":"d1dff91a-8d0a-402d-9c49-6f355159ff17","name":"Generic Concrete Gloves","color":"azure","price":131,"description":"The Football Is Good For Training And Recreational Purposes","thumbnailUrl":"http://placeimg.com/400/400","createAt":1631276403932,"updateAt":1631276403932},{"categoryId":"bd82d69a-d2f5-4dff-86fd-23ad8dca6b12","id":"3bfa5813-ebbc-47f7-8718-1f27dabc867a","name":"Small Frozen Gloves","color":"lime","price":713,"description":"Carbonite web goalkeeper gloves are ergonomically designed to give easy fit","thumbnailUrl":"http://placeimg.com/400/400","createAt":1631276403932,"updateAt":1631276403932},{"categoryId":"bd82d69a-d2f5-4dff-86fd-23ad8dca6b12","id":"27c240fa-32be-4f9b-8014-831ee62f7473","name":"Generic Granite Car","color":"green","price":573,"description":"New ABC 13 9370, 13.3, 5th Gen CoreA5-8250U, 8GB RAM, 256GB SSD, power UHD Graphics, OS 10 Home, OS Office A & J 2016","thumbnailUrl":"http://placeimg.com/400/400","createAt":1631276403932,"updateAt":1631276403932},{"categoryId":"bd82d69a-d2f5-4dff-86fd-23ad8dca6b12","id":"87dd38a0-b0e3-40d2-95e7-856d08d17437","name":"Gorgeous Metal Bike","color":"magenta","price":736,"description":"The automobile layout consists of a front-engine design, with transaxle-type transmissions mounted at the rear of the engine and four wheel drive","thumbnailUrl":"http://placeimg.com/400/400","createAt":1631276403932,"updateAt":1631276403932}],"profile":{"name":"Po"}}